README.md
license.txt
setup.py
Adpro_video_ferramentas/Adcamera.py
Adpro_video_ferramentas/Advideo.py
Adpro_video_ferramentas/__init__.py
adpro_video_ferramentas_Adbreyk_24_ad.egg-info/PKG-INFO
adpro_video_ferramentas_Adbreyk_24_ad.egg-info/SOURCES.txt
adpro_video_ferramentas_Adbreyk_24_ad.egg-info/dependency_links.txt
adpro_video_ferramentas_Adbreyk_24_ad.egg-info/top_level.txt