Metadata-Version: 2.4
Name: adpro-video-ferramentas-Adbreyk-24-ad
Version: 1.0
Summary: Este pacote irá fornecer ferramentas de processamento de vídeo
Author: Adbreyk
Author-email: 2333adbreyk@gmail.com
Keywords: Camera,Vídeo,processamento
License-File: license.txt
Dynamic: author
Dynamic: author-email
Dynamic: description
Dynamic: keywords
Dynamic: license-file
Dynamic: summary
